datargsing/__init__.py
datargsing/datargsing.py
datargsing/datargsing_core.py
datargsing/datargsing_tools.py
datargsing/datargsing_version.py
Datargsing-0.2.15.dist-info/LICENSE
Datargsing-0.2.15.dist-info/METADATA
Datargsing-0.2.15.dist-info/WHEEL
Datargsing-0.2.15.dist-info/top_level.txt
Datargsing-0.2.15.dist-info/RECORD
