Metadata-Version: 2.1
Name: Datargsing
Version: 0.2.15
Summary: A Data management and manipulation library
Home-page: https://github.com/LTHCTheMaster/Datargsing
Author: LTHC The Master (CHOSSY Lucas)
Maintainer: LTHC The Master (CHOSSY Lucas)
License: MIT
Classifier: Programming Language :: Python :: 3
Classifier: License :: OSI Approved :: MIT License
Requires-Python: >=3.11.1
License-File: LICENSE
